README.md
setup.py
fab_admin/__init__.py
fab_admin/commands.py
fab_admin/config.py
fab_admin/config_local.py
fab_admin/console.py
fab_admin/formats.py
fab_admin/log.py
fab_admin/models.py
fab_admin/monkey_patch.py
fab_admin/myredis.py
fab_admin/security_manager.py
fab_admin/utils.py
fab_admin/version.py
fab_admin/views.py
fab_admin.egg-info/PKG-INFO
fab_admin.egg-info/SOURCES.txt
fab_admin.egg-info/dependency_links.txt
fab_admin.egg-info/entry_points.txt
fab_admin.egg-info/not-zip-safe
fab_admin.egg-info/requires.txt
fab_admin.egg-info/top_level.txt
fab_admin/addon/confcenter/views_confcenter.py
fab_admin/addon/confcenter/__pycache__/views_confcenter.cpython-36.pyc
fab_admin/addon/confcenter/public/viewui/api.js
fab_admin/addon/confcenter/public/viewui/confcenter.vue
fab_admin/addon/confcenter/public/viewui/confcentermanage.vue
fab_admin/addon/confcenter/public/viewui/index.js
fab_admin/addon/confcenter/public/viewui/route.js
fab_admin/addon/confcenter/public/viewui/store.js
fab_admin/addon/confcenter/public/viewui/components/confperm.vue
fab_admin/addon/confcenter/public/viewui/components/conftable.vue
fab_admin/addon/queue/__init__.py
fab_admin/addon/queue/queues.py
fab_admin/addon/queue/views_queues.py
fab_admin/addon/queue/__pycache__/__init__.cpython-36.pyc
fab_admin/addon/queue/__pycache__/queues.cpython-36.pyc
fab_admin/addon/queue/__pycache__/views_queues.cpython-36.pyc
fab_admin/addon/sse/__init__.py
fab_admin/addon/sse/manager.py
fab_admin/addon/sse/models.py
fab_admin/addon/sse/sse.py
fab_admin/addon/sse/version.py
fab_admin/addon/sse/views.py
fab_admin/addon/sse/__pycache__/__init__.cpython-36.pyc
fab_admin/addon/sse/__pycache__/manager.cpython-36.pyc
fab_admin/addon/sse/__pycache__/sse.cpython-36.pyc
fab_admin/addon/sse/__pycache__/views.cpython-36.pyc
fab_admin/addon/sse/public/viewui/index.js
fab_admin/addon/sse/public/viewui/route.js
fab_admin/addon/sse/public/viewui/sse.vue
fab_admin/app_templates/Dockerfile
fab_admin/app_templates/README.rst
fab_admin/app_templates/build.gradle
fab_admin/app_templates/config.py
fab_admin/app_templates/config_base.py
fab_admin/app_templates/config_local.py
fab_admin/app_templates/docker-compose-build.yml
