Metadata-Version: 2.1
Name: fab-admin
Version: 0.1.5
Summary: UNKNOWN
Home-page: UNKNOWN
Author: Shawn Chen
Author-email: cwvinus@163.com
License: BSD
Platform: any
Classifier: Development Status :: 5 - Production/Stable
Classifier: Environment :: Web Environment
Classifier: Intended Audience :: Developers
Classifier: License :: OSI Approved :: BSD License
Classifier: Operating System :: OS Independent
Classifier: Programming Language :: Python
Classifier: Topic :: Software Development :: Libraries :: Python Modules
